issue_db_api/Cargo.toml
issue_db_api/__init__.py
issue_db_api/issue_api.cp310-win_amd64.pyd
issue_db_api/issue_api.pyi
issue_db_api/src/api_core.rs
issue_db_api/src/comments.rs
issue_db_api/src/config.rs
issue_db_api/src/embedding.rs
issue_db_api/src/errors.rs
issue_db_api/src/files.rs
issue_db_api/src/issues.rs
issue_db_api/src/labels.rs
issue_db_api/src/lib.rs
issue_db_api/src/models.rs
issue_db_api/src/projects.rs
issue_db_api/src/query.rs
issue_db_api/src/repository.rs
issue_db_api/src/schemas.rs
issue_db_api/src/tags.rs
issue_db_api/src/util.rs
issue_db_api/src/schemas/raw_issue_response.rs
issue_db_api-0.10.3.dist-info/LICENSE
issue_db_api-0.10.3.dist-info/METADATA
issue_db_api-0.10.3.dist-info/WHEEL
issue_db_api-0.10.3.dist-info/top_level.txt
issue_db_api-0.10.3.dist-info/RECORD
