Metadata-Version: 2.1
Name: issue_db_api
Version: 0.10.3
Author: Jesse Maarleveld
Classifier: Programming Language :: Rust
Classifier: Programming Language :: Python :: Implementation :: CPython
Classifier: Programming Language :: Python :: Implementation :: PyPy
Requires-Python: >=3.10
License-File: LICENSE
